azure/keyvault/secrets/__init__.py
azure/keyvault/secrets/_client.py
azure/keyvault/secrets/_models.py
azure/keyvault/secrets/_sdk_moniker.py
azure/keyvault/secrets/_version.py
azure/keyvault/secrets/py.typed
azure/keyvault/secrets/_generated/__init__.py
azure/keyvault/secrets/_generated/_client.py
azure/keyvault/secrets/_generated/_configuration.py
azure/keyvault/secrets/_generated/_patch.py
azure/keyvault/secrets/_generated/_serialization.py
azure/keyvault/secrets/_generated/_vendor.py
azure/keyvault/secrets/_generated/py.typed
azure/keyvault/secrets/_generated/_operations/__init__.py
azure/keyvault/secrets/_generated/_operations/_operations.py
azure/keyvault/secrets/_generated/_operations/_patch.py
azure/keyvault/secrets/_generated/aio/__init__.py
azure/keyvault/secrets/_generated/aio/_client.py
azure/keyvault/secrets/_generated/aio/_configuration.py
azure/keyvault/secrets/_generated/aio/_patch.py
azure/keyvault/secrets/_generated/aio/_vendor.py
azure/keyvault/secrets/_generated/aio/_operations/__init__.py
azure/keyvault/secrets/_generated/aio/_operations/_operations.py
azure/keyvault/secrets/_generated/aio/_operations/_patch.py
azure/keyvault/secrets/_generated/models/__init__.py
azure/keyvault/secrets/_generated/models/_enums.py
azure/keyvault/secrets/_generated/models/_models.py
azure/keyvault/secrets/_generated/models/_patch.py
azure/keyvault/secrets/_shared/__init__.py
azure/keyvault/secrets/_shared/_polling.py
azure/keyvault/secrets/_shared/_polling_async.py
azure/keyvault/secrets/_shared/async_challenge_auth_policy.py
azure/keyvault/secrets/_shared/async_client_base.py
azure/keyvault/secrets/_shared/challenge_auth_policy.py
azure/keyvault/secrets/_shared/client_base.py
azure/keyvault/secrets/_shared/http_challenge.py
azure/keyvault/secrets/_shared/http_challenge_cache.py
azure/keyvault/secrets/aio/__init__.py
azure/keyvault/secrets/aio/_client.py
azure_keyvault_secrets-4.8.0.dist-info/LICENSE
azure_keyvault_secrets-4.8.0.dist-info/METADATA
azure_keyvault_secrets-4.8.0.dist-info/WHEEL
azure_keyvault_secrets-4.8.0.dist-info/top_level.txt
azure_keyvault_secrets-4.8.0.dist-info/RECORD
